mbundle1/__init__.py
mbundle1/t1.py
mbundle1-0.1.4.dist-info/WHEEL
mbundle1-0.1.4.dist-info/METADATA
mbundle1-0.1.4.dist-info/RECORD
